{"npcs":[[null,null,null],[null,null,null,null,null,null,null,null,null,null,null,null,null,null,null,null,null,null,null],[null,null,null,null,null,null,null,null,null,null,null,null,null,null,null,null,null,null,null,null],[null,null,null,null,null,null,null,null,null,null,null,null,null,null,null,null,null,null,null],[null,{"x":4,"y":1,"tint":11181994.290532412,"lastAction":1415853249086,"speed":1},null,null,null,null,null,null,null,null,null,null,null,null,null,null,{"x":4,"y":16,"tint":14020948.50608317,"lastAction":1415853249086,"speed":1},null,null],[null,null,null,null,null,null,null,null,null,null,null,null,null,null,null,null,null,null],[],[null,null,{"x":7,"y":2,"tint":8563455.073562646,"lastAction":1415853249086,"speed":1},null,null,null,null,null,null,null,null,null,null,null,null,null,null,null,null,null],[null,null,null,null,null,null,null,null,null,null,null,null,null,null,null,null,null,null,null,null],[null,null,null,null,null,null,null,null,null,null,null,null,null,null,null,null,null,null,null,null],[null,null,null,null,null,null,null,null,null,null,null,null,null,null,null,null,null,null,null],[{"x":11,"y":0,"tint":14410436.855914729,"lastAction":1415853249086,"speed":1},null,null,null,null,null,null,null,null],[null,null,null,null,null,null],[null,null,null,{"x":13,"y":3,"tint":15582395.4462168,"lastAction":1415853249086,"speed":1},null,null,null,null,null,null],[null,null,null,null,null,null,null,null,null,null],[null,null,null,null,null,null,null,null,null,null,null],[null,null,null,null,null,null,null,null,null,null],[null,null,null,null,null,null,null],[null,null,null,null,null,null,null],[null,null,null]],"players":[[],[],[null,null,null,null,null,null,null,null,null,null,null,null,null,null,null,null,{"x":5,"y":5,"tint":13729420.441428348,"lastAction":1415821993940,"speed":5,"inventory":[1,1,1,1,0,0,0,0,0,1,0,0,1]}],[],[],[],[],[],[],[],[],[],[],[],[],[],[],[],[],[]],"bags":[[],[],[],[],[],[],[],[],[],[],[],[],[],[],[],[],[],[],[],[]],"ground":[[1,1,0,0,1,0,0,1,1,0,1,1,1,1,1,1,1,1,1,1],[1,1,1,1,1,1,1,1,0,1,1,1,0,1,1,1,1,1,1,1],[1,1,1,1,0,1,1,1,1,1,1,1,1,1,0,1,1,1,1,1],[0,1,0,1,0,1,1,1,0,1,1,0,1,0,1,1,1,1,1,1],[0,1,0,1,0,0,1,1,1,1,1,1,1,1,0,1,1,0,1,1],[0,1,0,1,1,0,1,1,1,0,1,1,1,1,1,1,1,1,1,1],[1,1,1,1,1,1,1,1,1,0,1,1,1,0,1,1,1,0,1,1],[1,1,1,0,1,1,0,1,1,1,1,0,1,1,1,0,0,1,0,0],[0,1,0,0,1,0,0,1,0,1,0,1,0,1,1,1,1,1,1,1],[0,1,0,1,1,1,1,1,1,0,0,1,1,1,1,1,1,1,0,1],[0,0,0,1,1,1,0,1,1,1,1,1,0,1,0,0,0,0,1,1],[1,1,1,1,1,1,0,1,0,1,0,0,0,1,1,1,1,0,0,1],[0,0,1,1,1,0,1,1,1,1,0,1,1,0,0,0,1,1,1,0],[1,0,1,1,1,1,1,1,1,1,1,0,0,0,1,1,1,1,1,1],[1,0,1,1,1,0,1,0,1,1,1,1,1,1,1,1,1,0,1,0],[1,1,1,1,0,1,0,1,1,1,1,1,1,1,0,1,0,1,0,1],[1,1,1,1,1,1,0,1,0,1,1,1,0,1,0,1,1,1,0,1],[1,0,0,0,0,1,1,0,0,1,1,1,1,1,1,0,1,0,1,1],[1,1,0,0,1,0,0,1,1,1,0,0,1,1,0,1,1,1,1,1],[1,1,1,1,0,1,1,1,0,1,1,1,0,1,0,1,1,0,1,0]],"objects":[[0,0,1,1,0,1,1,0,0,1,0,0,0,2,0,0,0,0,0,2],[0,0,0,0,2,0,0,0,1,0,0,0,1,0,0,0,0,0,0,2],[0,0,0,0,1,0,0,0,0,0,0,0,0,0,1,0,0,0,0,0],[1,0,1,0,1,0,0,0,1,0,0,1,0,1,0,0,0,0,0,0],[1,0,1,0,1,1,2,0,0,0,0,0,0,0,1,0,0,1,0,0],[1,0,1,0,0,1,2,0,0,1,0,0,0,0,0,0,0,0,0,0],[2,0,0,0,0,0,0,0,0,1,0,0,0,1,0,0,0,1,0,0],[0,0,0,1,0,0,1,0,0,0,0,1,0,0,0,1,1,0,1,1],[1,0,1,1,2,1,1,0,1,0,1,2,1,0,0,0,0,0,2,0],[1,0,1,2,0,0,0,0,0,1,1,0,0,0,0,0,0,0,1,0],[1,1,1,0,0,0,1,0,0,0,0,0,1,0,1,1,1,1,0,0],[0,2,0,0,0,0,1,0,1,2,1,1,1,0,2,0,0,1,1,0],[1,1,0,2,0,1,0,0,0,0,1,0,0,1,1,1,0,0,0,1],[0,1,0,0,0,0,0,2,0,0,0,1,1,1,0,0,0,0,0,2],[0,1,0,2,0,1,0,1,0,0,0,2,0,0,2,0,0,1,0,1],[0,0,0,0,1,0,1,0,0,0,0,0,0,0,1,2,1,0,1,0],[0,0,2,0,0,0,1,0,1,0,0,2,1,0,1,0,0,0,1,0],[0,1,1,1,1,0,0,1,1,0,0,0,0,0,0,1,0,1,0,0],[0,0,1,1,0,1,1,0,0,0,1,1,0,2,1,2,2,0,0,0],[0,0,0,0,1,0,0,0,1,0,0,0,1,0,1,0,0,1,0,1]]}